dados_moeda/__init__.py
dados_moeda/data_transform.py
dados_moeda/validate_data.py
dados_moeda-0.0.1.dist-info/METADATA
dados_moeda-0.0.1.dist-info/WHEEL
dados_moeda-0.0.1.dist-info/top_level.txt
dados_moeda-0.0.1.dist-info/RECORD
