Metadata-Version: 2.1
Name: dados_moeda
Version: 0.0.1
Summary: Data conversion
Home-page: https://github.com/rodrigo1708/dados_moeda.git
Author: Rodrigo França
Author-email: rodrigo_franca92@hotmail.com
Requires-Python: >=3.8
